odoo10_addon_partner_contact_nutrition_goal-10.0.1.0.0-py2.7-nspkg.pth
odoo/addons/partner_contact_nutrition_goal/README.rst
odoo/addons/partner_contact_nutrition_goal/__init__.py
odoo/addons/partner_contact_nutrition_goal/__manifest__.py
odoo/addons/partner_contact_nutrition_goal/i18n/am.po
odoo/addons/partner_contact_nutrition_goal/i18n/ar.po
odoo/addons/partner_contact_nutrition_goal/i18n/bg.po
odoo/addons/partner_contact_nutrition_goal/i18n/bs.po
odoo/addons/partner_contact_nutrition_goal/i18n/ca.po
odoo/addons/partner_contact_nutrition_goal/i18n/cs.po
odoo/addons/partner_contact_nutrition_goal/i18n/da.po
odoo/addons/partner_contact_nutrition_goal/i18n/de.po
odoo/addons/partner_contact_nutrition_goal/i18n/el_GR.po
odoo/addons/partner_contact_nutrition_goal/i18n/en_GB.po
odoo/addons/partner_contact_nutrition_goal/i18n/es.po
odoo/addons/partner_contact_nutrition_goal/i18n/es_CR.po
odoo/addons/partner_contact_nutrition_goal/i18n/es_EC.po
odoo/addons/partner_contact_nutrition_goal/i18n/es_MX.po
odoo/addons/partner_contact_nutrition_goal/i18n/es_VE.po
odoo/addons/partner_contact_nutrition_goal/i18n/et.po
odoo/addons/partner_contact_nutrition_goal/i18n/fi.po
odoo/addons/partner_contact_nutrition_goal/i18n/fr.po
odoo/addons/partner_contact_nutrition_goal/i18n/fr_CA.po
odoo/addons/partner_contact_nutrition_goal/i18n/gl.po
odoo/addons/partner_contact_nutrition_goal/i18n/hr.po
odoo/addons/partner_contact_nutrition_goal/i18n/hr_HR.po
odoo/addons/partner_contact_nutrition_goal/i18n/hu.po
odoo/addons/partner_contact_nutrition_goal/i18n/it.po
odoo/addons/partner_contact_nutrition_goal/i18n/ja.po
odoo/addons/partner_contact_nutrition_goal/i18n/lt.po
odoo/addons/partner_contact_nutrition_goal/i18n/lv.po
odoo/addons/partner_contact_nutrition_goal/i18n/mk.po
odoo/addons/partner_contact_nutrition_goal/i18n/mn.po
odoo/addons/partner_contact_nutrition_goal/i18n/nb.po
odoo/addons/partner_contact_nutrition_goal/i18n/nb_NO.po
odoo10_addon_partner_contact_nutrition_goal-10.0.1.0.0.dist-info/DESCRIPTION.rst
odoo10_addon_partner_contact_nutrition_goal-10.0.1.0.0.dist-info/METADATA
odoo10_addon_partner_contact_nutrition_goal-10.0.1.0.0.dist-info/RECORD
odoo10_addon_partner_contact_nutrition_goal-10.0.1.0.0.dist-info/WHEEL
odoo10_addon_partner_contact_nutrition_goal-10.0.1.0.0.dist-info/metadata.json
odoo10_addon_partner_contact_nutrition_goal-10.0.1.0.0.dist-info/namespace_packages.txt
odoo10_addon_partner_contact_nutrition_goal-10.0.1.0.0.dist-info/top_level.txt
